pf9/__init__.py
pf9/exceptions.py
pf9/express.py
pf9/cli/__init__.py
pf9/cli/commands.py
pf9/cluster/__init__.py
pf9/cluster/cluster_attach.py
pf9/cluster/cluster_create.py
pf9/cluster/commands.py
pf9/cluster/helpers.py
pf9/config/__init__.py
pf9/config/commands.py
pf9/inventory/__init__.py
pf9/inventory/commands.py
pf9/modules/__init__.py
pf9/modules/express.py
pf9/modules/ostoken.py
pf9/modules/util.py
pf9/support/__init__.py
pf9/support/commands.py
pf9/templates/pmk_inventory.tpl
express_cli-0.2.2.dist-info/LICENSE
express_cli-0.2.2.dist-info/METADATA
express_cli-0.2.2.dist-info/WHEEL
express_cli-0.2.2.dist-info/entry_points.txt
express_cli-0.2.2.dist-info/top_level.txt
express_cli-0.2.2.dist-info/RECORD
