Metadata-Version: 2.1
Name: express-cli
Version: 0.2.2
Summary: Express CLI.
Home-page: https://github.com/platform9/express-cli
Author: Jeremy Brooks
Author-email: jeremy@platform9.com
License: Apache 2.0
Keywords: cli
Platform: UNKNOWN
Classifier: Intended Audience :: System Administrators
Classifier: Intended Audience :: End Users/Desktop
Classifier: Intended Audience :: Developers
Classifier: Topic :: Utilities
Classifier: License :: OSI Approved :: Apache Software License
Classifier: Natural Language :: English
Classifier: Operating System :: OS Independent
Classifier: Programming Language :: Python :: 2
Classifier: Programming Language :: Python :: 2.6
Classifier: Programming Language :: Python :: 2.7
Classifier: Programming Language :: Python :: 3
Classifier: Programming Language :: Python :: 3.2
Classifier: Programming Language :: Python :: 3.3
Classifier: Programming Language :: Python :: 3.4
Requires-Dist: click
Requires-Dist: prettytable
Requires-Dist: requests
Requires-Dist: netifaces
Requires-Dist: colorama
Requires-Dist: urllib3
Requires-Dist: paramiko
Requires-Dist: fabric
Requires-Dist: invoke
Provides-Extra: test
Requires-Dist: coverage ; extra == 'test'
Requires-Dist: pytest ; extra == 'test'
Requires-Dist: pytest-cov ; extra == 'test'
Requires-Dist: mock ; extra == 'test'
